dashml/__init__.py
dashml/builder.py
dashml/clean.py
dashml/core.py
dashml/html.py
dashml/types.py
dashml-0.1.1.dist-info/LICENSE
dashml-0.1.1.dist-info/METADATA
dashml-0.1.1.dist-info/WHEEL
dashml-0.1.1.dist-info/top_level.txt
dashml-0.1.1.dist-info/RECORD
