Metadata-Version: 2.1
Name: dashml
Version: 0.1.1
Summary: Generate HTML with Python functions.
Home-page: https://github.com/madelyneriksen/dashml
Author: Madelyn Eriksen
Author-email: opensource@madelyneriksen.com
License: UNKNOWN
Platform: UNKNOWN
Classifier: Programming Language :: Python :: 3
Classifier: License :: OSI Approved :: MIT License
Classifier: Operating System :: OS Independent
Requires-Python: >=3.5
Requires-Dist: lxml
